Workbook
Name Slicer_Product_Category: #N/A
Name Slicer_Product_Name: #N/A
Name Slicer_Region: #N/A
Name Slicer_State: #N/A

Sheet Dashboard
A1: FMCG MIS DASHBOARD
A2: Performance Analytics & Sales Trends | H1 2026 (Jan - Jun)
F4: TOTAL NET SALES | I4: TARGET ACHIEVEMENT % | L4: TOTAL UNITS SOLD | O4: PENDING COLLECTION
F5: =GETPIVOTDATA("Sum of Net Sales",'Pivot Tables'!$A$4) -> 9340517.8 | I5: =IFERROR('Pivot Tables'!H9,'Pivot Tables'!H6) -> 0.99502686 | L5: =GETPIVOTDATA("Sum of Units Sold",'Pivot Tables'!$E$14) -> 98252 | O5: =GETPIVOTDATA("Net Sales",'Pivot Tables'!$P$14,"Payment Status","Pending") -> 4244352.4

Sheet Sales Data
A1: Date | B1: Invoice No | C1: Distributor | D1: Region | E1: State | F1: Sales Executive | G1: Product Category | H1: Product Name | I1: Units Sold | J1: Unit Price | K1: Discount % | L1: Gross Sales | M1: Net Sales | N1: Target Sales | O1: Achievement % | P1: Payment Status | Q1: Month Name
A2: 46103 | B2: INV00002 | C2: Future | D2: West | E2: GJ | F2: Akhil | G2: Personal Care | H2: Soap | I2: 136 | J2: 35 | K2: 0.06 | L2: 4760 | M2: 4474.4 | N2: 3897.22 | O2: 1.15 | P2: Paid | Q2: Mar 2026
A3: 46148 | B3: INV00003 | C3: Elite | D3: East | E3: WB | F3: Sneha | G3: Beverages | H3: Coffee | I3: 36 | J3: 250 | K3: 0.07 | L3: 9000 | M3: 8370 | N3: 8297.73 | O3: 1.01 | P3: Paid | Q3: May 2026
A4: 46048 | B4: INV00004 | C4: Alpha | D4: South | E4: AP | F4: Priya | G4: Personal Care | H4: Shampoo | I4: 129 | J4: 180 | K4: 0.15 | L4: 23220 | M4: 19737 | N4: 23580.88 | O4: 0.84 | P4: Paid | Q4: Jan 2026
A5: 46118 | B5: INV00005 | C5: Elite | D5: East | E5: OD | F5: Priya | G5: Beverages | H5: Coffee | I5: 148 | J5: 250 | K5: 0.1 | L5: 37000 | M5: 33300 | N5: 39038.34 | O5: 0.85 | P5: Paid | Q5: Apr 2026
A6: 46174 | B6: INV00006 | C6: Central | D6: South | E6: TN | F6: Priya | G6: Beverages | H6: Tea | I6: 166 | J6: 120 | K6: 0.09 | L6: 19920 | M6: 18127.2 | N6: 17587.9 | O6: 1.03 | P6: Paid | Q6: Jun 2026
A7: 46146 | B7: INV00007 | C7: Bravo | D7: North | E7: PB | F7: Sneha | G7: Beverages | H7: Coffee | I7: 50 | J7: 250 | K7: 0.01 | L7: 12500 | M7: 12375 | N7: 12993.25 | O7: 0.95 | P7: Paid | Q7: May 2026
A8: 46170 | B8: INV00008 | C8: Alpha | D8: South | E8: TS | F8: Kiran | G8: Snacks | H8: Biscuits | I8: 156 | J8: 30 | K8: 0.11 | L8: 4680 | M8: 4165.2 | N8: 4633.27 | O8: 0.9 | P8: Paid | Q8: May 2026
A9: 46152 | B9: INV00009 | C9: Future | D9: South | E9: TN | F9: Sneha | G9: Personal Care | H9: Shampoo | I9: 27 | J9: 180 | K9: 0.12 | L9: 4860 | M9: 4276.8 | N9: 3498.66 | O9: 1.22 | P9: Pending | Q9: May 2026
A10: 46078 | B10: INV00010 | C10: Delta | D10: North | E10: PB | F10: Sneha | G10: Snacks | H10: Chips | I10: 155 | J10: 40 | K10: 0.13 | L10: 6200 | M10: 5394 | N10: 4343.41 | O10: 1.24 | P10: Pending | Q10: Feb 2026
A11: 46131 | B11: INV00011 | C11: Delta | D11: East | E11: WB | F11: Sneha | G11: Beverages | H11: Tea | I11: 118 | J11: 120 | K11: 0.02 | L11: 14160 | M11: 13876.8 | N11: 15542.42 | O11: 0.89 | P11: Paid | Q11: Apr 2026
A12: 46176 | B12: INV00012 | C12: Elite | D12: West | E12: GJ | F12: Ravi | G12: Snacks | H12: Biscuits | I12: 43 | J12: 30 | K12: 0.09 | L12: 1290 | M12: 1173.9 | N12: 1113.18 | O12: 1.05 | P12: Pending | Q12: Jun 2026
A13: 46075 | B13: INV00013 | C13: Future | D13: West | E13: MH | F13: Priya | G13: Personal Care | H13: Soap | I13: 117 | J13: 35 | K13: 0.1 | L13: 4095 | M13: 3685.5 | N13: 3270.38 | O13: 1.13 | P13: Pending | Q13: Feb 2026
... A1001: 46101 | B1001: INV01001 | C1001: Alpha | D1001: West | E1001: MH | F1001: Priya | G1001: Personal Care | H1001: Soap | I1001: 20 | J1001: 35 | K1001: 0.14 | L1001: 700 | M1001: 602 | N1001: 618.43 | O1001: 0.97 | P1001: Pending | Q1001: Mar 2026

Sheet Inventory
A1: Product | B1: Opening Stock | C1: Sales Qty | D1: Closing Stock | E1: Reorder Level | F1: Stock Status
A2: Tea | B2: 1455 | C2: 803 | D2: 652 | E2: 300 | F2: =IF(D2<E2,"Reorder","Available") -> Available
A3: Coffee | B3: 755 | C3: 137 | D3: 618 | E3: 300 | F3: =IF(D3<E3,"Reorder","Available") -> Available
A4: Chips | B4: 1568 | C4: 719 | D4: 849 | E4: 300 | F4: =IF(D4<E4,"Reorder","Available") -> Available
A5: Biscuits | B5: 1865 | C5: 1307 | D5: 558 | E5: 300 | F5: =IF(D5<E5,"Reorder","Available") -> Available
A6: Soap | B6: 1812 | C6: 811 | D6: 1001 | E6: 300 | F6: =IF(D6<E6,"Reorder","Available") -> Available
A7: Shampoo | B7: 1140 | C7: 223 | D7: 917 | E7: 300 | F7: =IF(D7<E7,"Reorder","Available") -> Available

Sheet Pivot Tables
A3: Category Performance | E3: Regional Performance vs Target
A4: Product Category | B4: Sum of Net Sales | C4: % Share | E4: Region | F4: Sum of Net Sales | G4: Sum of Target Sales | H4: Ach % | J4: Sum of Units Sold | K4: Column Labels
A5: Beverages | B5: 4891483.1 | C5: 0.52368436 | E5: East | F5: 2518743.1 | G5: 2542442.5 | H5: =F5/G5 -> 0.99067851 | J5: Product Category | K5: Biscuits | L5: Chips | M5: Coffee | N5: Shampoo | O5: Soap | P5: Tea | Q5: Grand Total
A6: Personal Care | B6: 3339849.8 | C6: 0.35756581 | E6: North | F6: 2292004.2 | G6: 2321992.1 | H6: =F6/G6 -> 0.98708528 | J6: Jan | K6: 1942 | L6: 3609 | M6: 2074 | N6: 3548 | O6: 2092 | P6: 1428 | Q6: 14693
A7: Snacks | B7: 1109184.9 | C7: 0.11874983 | E7: South | F7: 2205749.5 | G7: 2237089.9 | H7: =F7/G7 -> 0.98599057 | J7: Feb | K7: 3615 | L7: 2614 | M7: 1949 | N7: 2353 | O7: 2800 | P7: 1834 | Q7: 15165
A8: Grand Total | B8: 9340517.8 | C8: 1 | E8: West | F8: 2324020.9 | G8: 2285677.2 | H8: =F8/G8 -> 1.0167756 | J8: Mar | K8: 4102 | L8: 1898 | M8: 1992 | N8: 2221 | O8: 3565 | P8: 2365 | Q8: 16143
E9: Grand Total | F9: 9340517.8 | G9: 9387201.7 | H9: =F9/G9 -> 0.99502686 | J9: Apr | K9: 2370 | L9: 3696 | M9: 2547 | N9: 1583 | O9: 3326 | P9: 2639 | Q9: 16161
J10: May | K10: 2300 | L10: 2967 | M10: 1847 | N10: 3240 | O10: 3955 | P10: 2878 | Q10: 17187
J11: Jun | K11: 2372 | L11: 2695 | M11: 3959 | N11: 3418 | O11: 3507 | P11: 2952 | Q11: 18903
J12: Grand Total | K12: 16701 | L12: 17479 | M12: 14368 | N12: 16363 | O12: 19245 | P12: 14096 | Q12: 98252
A13: Monthly Sales Trend (2026) | E13: Product Performance Breakdown
A14: Product Category | B14: Sum of Net Sales | C14: MoM Growth | E14: Product Category | F14: Sum of Net Sales | G14: Sum of Units Sold | J14: Product Category | K14: Sum of Units Sold | M14: Region | N14: Net Sales | P14: Product Category | Q14: Sum of Net Sales
A15: Jan | B15: 1493583.7 | C15: - | E15: Biscuits | F15: 462342.9 | G15: 16701 | J15: AP | K15: 5877 | M15: South | N15: =SUMIF('Sales Data'!D2:D1001,M15,'Sales Data'!M2:M1001) -> 2205749.5 | P15: Paid | Q15: 5096165.4
A16: Feb | B16: 1326844.4 | C16: =(B16-B15)/B15 -> -0.11163707 | E16: Chips | F16: 646842 | G16: 17479 | J16: DL | K16: 8558 | M16: North | N16: =SUMIF('Sales Data'!D2:D1001,M16,'Sales Data'!M2:M1001) -> 2292004.2 | P16: Pending | Q16: 4244352.4
A17: Mar | B17: 1394355.3 | C17: =(B17-B16)/B16 -> 0.050880874 | E17: Coffee | F17: 3326307.5 | G17: 14368 | J17: GJ | K17: 11215 | M17: West | N17: =SUMIF('Sales Data'!D2:D1001,M17,'Sales Data'!M2:M1001) -> 2324020.9 | P17: Grand Total | Q17: 9340517.8
A18: Apr | B18: 1460733.9 | C18: =(B18-B17)/B17 -> 0.047605225 | E18: Shampoo | F18: 2719281.6 | G18: 16363 | J18: HR | K18: 7650 | M18: East | N18: =SUMIF('Sales Data'!D2:D1001,M18,'Sales Data'!M2:M1001) -> 2518743.1
A19: May | B19: 1588763.1 | C19: =(B19-B18)/B18 -> 0.087647172 | E19: Soap | F19: 620568.2 | G19: 19245 | J19: KA | K19: 5112
A20: Jun | B20: 2076237.3 | C20: =(B20-B19)/B19 -> 0.30682623 | E20: Tea | F20: 1565175.6 | G20: 14096 | J20: MH | K20: 13514
A21: Grand Total | B21: 9340517.8 | C21: =(B21-B20)/B20 -> 3.4987717 | E21: Grand Total | F21: 9340517.8 | G21: 98252 | J21: OD | K21: 13081
J22: PB | K22: 8275
J23: TN | K23: 7147
J24: TS | K24: 5977
J25: WB | K25: 11846
J26: Grand Total | K26: 98252
